libusbmuxd/__init__.py
libusbmuxd-0.1.dist-info/WHEEL
libusbmuxd-0.1.dist-info/METADATA
libusbmuxd-0.1.dist-info/RECORD
