Metadata-Version: 2.1
Name: libusbmuxd
Version: 0.1
Summary: Python bindings for libusbmuxd
Home-page: https://github.com/libimobiledevice/python-libusbmuxd
License: UNKNOWN
Author: Rick Mark
Author-email: rickmark@guardianapp.com
